aish/__init__.py
aish/aish.py
aish/proxy.py
tests/__init__.py
tests/test_chat.py
aish-0.1.8.dist-info/LICENCE
aish-0.1.8.dist-info/METADATA
aish-0.1.8.dist-info/WHEEL
aish-0.1.8.dist-info/entry_points.txt
aish-0.1.8.dist-info/top_level.txt
aish-0.1.8.dist-info/RECORD
