Metadata-Version: 2.1
Name: aish
Version: 0.1.8
Summary: A command-line application that interacts with the OpenAI ChatGPT API.
Author: Toni Leino
Author-email: toni@leino.net
License-File: LICENCE
Requires-Dist: rich
Requires-Dist: flask
Requires-Dist: requests
Requires-Dist: distro
